Task2/LayeredTestbench/sq_root.sv
module sq_root (
    output reg [15:0] res,output reg done,output reg [3:0] cs,ns,
    input [15:0] num,input clk,reset,ready
);
    // Datapath
    // Bit
    reg bit_mux, reset_bit;
    reg [15:0] bit_shift_2, bit_in, bit1;
    always @(*) begin
        bit_in = bit_mux ? bit_shift_2 : bit1;
    end 

    always @(posedge clk ) begin
       if (reset_bit) begin
           bit1 <= 1 << 14;
       end 
       else begin
           bit1 <= bit_in;
       end
    end
    
    always @(*) begin
        bit_shift_2 = bit1 >> 2;
    end

    reg b_gt_n;

    always @(*) begin
        b_gt_n = bit1 > num;
    end
    // num
    reg b_ne_z;
    always @(*) begin
        b_ne_z = bit1 != 0;
    end

    reg num_mux, reset_num;
    reg [15:0] n_m_rb, num_in, num1;
    always @(*) begin
        num_in = num_mux ? n_m_rb : num1;
    end

    always @(posedge clk ) begin
        if (reset_num) begin
            num1 <= num;
        end
        else
            num1 <= num_in;
    end

    reg [15:0] res_p_bit;
    always @(*) begin
        n_m_rb = num1 - res_p_bit;
    end

    //res
    reg [1:0] res_mux;
    reg reset_res;
    reg [15:0] res_in, res1, res1a;
    always_comb begin 
            case (res_mux)
                2'd0: res_in = res;
                2'd1: res_in = res1;
                2'd2: res_in = res1a; 
                default: res_in = res;
            endcase
    end

    always @(posedge clk) begin
        if (reset_res) begin
            res <= 0;
        end
        else
            res <= res_in;
    end

    always @(*) begin
        res_p_bit = res + bit1;
    end

    reg n_gte_rb;
    always @(*) begin
        n_gte_rb = num1 >= res_p_bit;
    end
    
    always @(*) begin
        res1 = res >> 1;
    end

    always @(*) begin
        res1a = res1 + bit1;
    end


    // Controller
    // State Machine
    parameter s0 = 4'b0000;
    parameter s1 = 4'b0001;
    parameter s2 = 4'b0010;
    parameter s3 = 4'b0011;
    parameter s4 = 4'b0100;
    parameter s5 = 4'b0101;
    parameter s6 = 4'b0110;
    parameter s7 = 4'b0111;
    parameter s8 = 4'b1000;
    parameter s9 = 4'b1001;
    parameter s10 = 4'b1010;
    parameter s11 = 4'b1011;
    // State Resgister
    
    always @(posedge clk) begin
        if(reset) cs <=  s0;
        else cs <=  ns;
    end
    // Output Logic
        always_comb begin
            case (cs)
            s0: begin
                done = 0;
                bit_mux = 0;
                reset_bit = 1;
                reset_num = 1;
                reset_res = 1;
            end 

            s1: begin
                done = 0;
                bit_mux = 1;
                reset_bit = 0;
            end
            
            s2: begin
                done = 0;
                bit_mux = 0;
                reset_bit = 0;
            end
            s3: begin
                done = 0;
                bit_mux = 0;
                num_mux = 0;
                res_mux = 2'd0;
                reset_bit = 0;
            end
            s5: begin
                done = 0;
                bit_mux = 0;
                num_mux = 0;
                res_mux = 2'd0;
                reset_bit = 0;
                reset_num = 0;
                reset_res = 0;
            end
            s6: begin
                done = 0;
                bit_mux = 0;
                num_mux = 1;
                res_mux = 2'd0;
                reset_bit = 0;
                reset_num = 0;
                reset_res = 0;
            end
            s7: begin
                done = 0;
                bit_mux = 0;
                num_mux = 0;
                res_mux = 2'd2;
                reset_bit = 0;
                reset_num = 0;
                reset_res = 0;
            end
            s8: begin
                done = 0;
                bit_mux = 0;
                num_mux = 0;
                res_mux = 2'd1;
                reset_bit = 0;
                reset_num = 0;
                reset_res = 0;
            end
            s9: begin
                done = 0;
                bit_mux = 1;
                num_mux = 0;
                res_mux = 2'd0;
                reset_bit = 0;
                reset_num = 0;
                reset_res = 0;
            end
            s10: begin
                done = 1;
                bit_mux = 0;
                num_mux = 0;
                res_mux = 2'd0;
                reset_bit = 1;
                reset_num = 0;
                reset_res = 0;
            end
            default:  done = 0;
        endcase
        end
        
    // Next State Logic
    always @(*) begin
        case (cs)
            s0: ns = ready ? b_gt_n ? s1 : s3 : s0;
            s1: ns = s2;
            s2: ns = b_gt_n ? s1 : s3;
            s3: ns = b_ne_z ? s5 : s10;
            s5: ns = n_gte_rb ? s6 : s8;
            s6: ns = s7;
            s7: ns = s9;
            s8: ns = s9;
            s9: ns = s3;
            s10: ns = s0;
            default:  ns = s0;
        endcase
    end
    

endmodule

Task2/Layered/top.sv
`include "sq_root.sv"
module top (
    output reg [15:0] o_res,output reg o_done,output reg [3:0] o_cs,o_ns,
    input [15:0] i_num,input clk,rst,i_ready
);

    sq_root s1(
    .res(o_res),.done(o_done),.cs(o_cs),.ns(o_ns),
    .num(i_num),.clk(clk),.reset(rst),.ready(i_ready)
    );

    initial begin
        $dumpfile("dump.vcd");
        $dumpvars(0,top);
    end

endmodule

Task2/LayeredTestbench/dump.vcd
$date
	Tue Oct  5 21:46:08 2021
$end
$version
	Icarus Verilog
$end
$timescale
	1ps
$end
$scope module top $end
$var wire 1 ! clk $end
$var wire 16 " i_num [15:0] $end
$var wire 1 # i_ready $end
$var wire 1 $ rst $end
$var wire 16 % o_res [15:0] $end
$var wire 4 & o_ns [3:0] $end
$var wire 1 ' o_done $end
$var wire 4 ( o_cs [3:0] $end
$scope module s1 $end
$var wire 1 ! clk $end
$var wire 16 ) num [15:0] $end
$var wire 1 # ready $end
$var wire 1 $ reset $end
$var reg 1 * b_gt_n $end
$var reg 1 + b_ne_z $end
$var reg 16 , bit1 [15:0] $end
$var reg 16 - bit_in [15:0] $end
$var reg 1 . bit_mux $end
$var reg 16 / bit_shift_2 [15:0] $end
$var reg 4 0 cs [3:0] $end
$var reg 1 ' done $end
$var reg 1 1 n_gte_rb $end
$var reg 16 2 n_m_rb [15:0] $end
$var reg 4 3 ns [3:0] $end
$var reg 16 4 num1 [15:0] $end
$var reg 16 5 num_in [15:0] $end
$var reg 1 6 num_mux $end
$var reg 16 7 res [15:0] $end
$var reg 16 8 res1 [15:0] $end
$var reg 16 9 res1a [15:0] $end
$var reg 16 : res_in [15:0] $end
$var reg 2 ; res_mux [1:0] $end
$var reg 16 < res_p_bit [15:0] $end
$var reg 1 = reset_bit $end
$var reg 1 > reset_num $end
$var reg 1 ? reset_res $end
$upscope $end
$upscope $end
$enddefinitions $end
#0
$dumpvars
1?
1>
1=
bx <
bx ;
bx :
bx 9
bx 8
bx 7
x6
bx 5
bx 4
b0 3
bx 2
x1
b0 0
bx /
0.
bx -
bx ,
x+
x*
b0 )
b0 (
0'
b0 &
bx %
z$
0#
b0 "
1!
$end
#5000
0!
#10000
b100000000000000 9
bx00000000000000 5
b0 8
b0 :
01
b1100000000000000 2
b100000000000000 <
1+
b1000000000000 /
1*
b100000000000000 -
b0 %
b0 7
b0 4
b100000000000000 ,
1!
#15000
0!
#20000
b1 &
b1 3
b10000 "
b10000 )
1#
1!
#25000
0!
#30000
0#
b1000000000000 -
b10 &
b10 3
0=
1.
b1100000000010000 2
bx00000000010000 5
b1 (
b1 0
b10000 4
1!
#35000
0!
#40000
bx000000010000 5
b1111000000010000 2
b1000000000000 9
b1000000000000 <
b10000000000 /
b1 &
b1 3
0.
b1000000000000 ,
b10 (
b10 0
1!
#45000
0!
#50000
b10000000000 -
b10 &
b10 3
1.
b1 (
b1 0
1!
#55000
0!
#60000
bx0000010000 5
b1111110000010000 2
b10000000000 9
b10000000000 <
b100000000 /
b1 &
b1 3
0.
b10000000000 ,
b10 (
b10 0
1!
#65000
0!
#70000
b100000000 -
b10 &
b10 3
1.
b1 (
b1 0
1!
#75000
0!
#80000
bx00010000 5
b1111111100010000 2
b100000000 9
b100000000 <
b1000000 /
b1 &
b1 3
0.
b100000000 ,
b10 (
b10 0
1!
#85000
0!
#90000
b1000000 -
b10 &
b10 3
1.
b1 (
b1 0
1!
#95000
0!
#100000
bx010000 5
b1111111111010000 2
b1000000 9
b1000000 <
b10000 /
b1 &
b1 3
0.
b1000000 ,
b10 (
b10 0
1!
#105000
0!
#110000
b10000 -
b10 &
b10 3
1.
b1 (
b1 0
1!
#115000
0!
#120000
b0x0000 5
11
b0 2
b10000 9
b10000 <
b100 /
0*
b11 &
b11 3
0.
b10000 ,
b10 (
b10 0
1!
#125000
0!
#130000
b10000 5
b101 &
b101 3
b0 ;
06
b11 (
b11 0
1!
#135000
0!
#140000
b110 &
b110 3
0?
0>
b101 (
b101 0
1!
#145000
0!
#150000
b0 5
b111 &
b111 3
16
b110 (
b110 0
1!
#155000
0!
#160000
b10000 :
b1111111111110000 2
01
b1001 &
b1001 3
b10 ;
06
b0 4
b111 (
b111 0
1!
#165000
0!
#170000
b100 -
b11000 9
b1111111111100000 2
b11 &
b11 3
b0 ;
1.
b1000 8
b100000 <
b1001 (
b1001 0
b10000 %
b10000 7
1!
#175000
0!
#180000
b1111111111101100 2
b1100 9
b10100 <
b1 /
b101 &
b101 3
0.
b100 ,
b11 (
b11 0
1!
#185000
0!
#190000
b1000 &
b1000 3
b101 (
b101 0
1!
#195000
0!
#200000
b1000 :
b1001 &
b1001 3
b1 ;
b1000 (
b1000 0
1!
#205000
0!
#210000
b1 -
b1000 9
b1111111111110100 2
b11 &
b11 3
b0 ;
1.
b100 8
b1100 <
b1001 (
b1001 0
b1000 %
b1000 7
1!
#215000
0!
#220000
b1111111111110111 2
b101 9
b1001 <
b0 /
b101 &
b101 3
0.
b1 ,
b11 (
b11 0
1!
#225000
0!
#230000
b1000 &
b1000 3
b101 (
b101 0
1!
#235000
0!
#240000
b100 :
b1001 &
b1001 3
b1 ;
b1000 (
b1000 0
1!
#245000
0!
#250000
b0 -
b11 9
b1111111111111011 2
b11 &
b11 3
b0 ;
1.
b10 8
b101 <
b1001 (
b1001 0
b100 %
b100 7
1!
#255000
0!
#260000
b1111111111111100 2
b10 9
b100 <
0+
b1010 &
b1010 3
0.
b0 ,
b11 (
b11 0
1!
#265000
0!
#270000
b0 &
b0 3
1=
1'
b1010 (
b1010 0
1!
#275000
0!
#280000
b1011111111111100 2
b100000000000010 9
b100000000000100 <
b1000000000000 /
1+
1*
b100000000000000 -
1?
1>
0'
b100000000000000 ,
b0 (
b0 0
1!
#285000
0!
#290000
b1 &
b1 3
b1010001 "
b1010001 )
1#
b100000000000000 9
b0 8
b100000000000000 <
b0 :
b1100000000010000 2
b10000 5
b0 %
b0 7
b10000 4
1!
#295000
0!
#300000
0#
b1000000000000 -
b1100000001010001 2
b1010001 5
b10 &
b10 3
0=
1.
b1010001 4
b1 (
b1 0
1!
#305000
0!
#310000
b1111000001010001 2
b1 &
b1 3
0.
b1000000000000 9
b1000000000000 <
b10000000000 /
b10 (
b10 0
b1000000000000 ,
1!
#315000
0!
#320000
b10000000000 -
b10 &
b10 3
1.
b1 (
b1 0
1!
#325000
0!
#330000
b1111110001010001 2
b1 &
b1 3
0.
b10000000000 9
b10000000000 <
b100000000 /
b10 (
b10 0
b10000000000 ,
1!
#335000
0!
#340000
b100000000 -
b10 &
b10 3
1.
b1 (
b1 0
1!
#345000
0!
#350000
b1111111101010001 2
b1 &
b1 3
0.
b100000000 9
b100000000 <
b1000000 /
b10 (
b10 0
b100000000 ,
1!
#355000
0!
#360000
b1000000 -
b10 &
b10 3
1.
b1 (
b1 0
1!
#365000
0!
#370000
b10001 2
11
b11 &
b11 3
0.
b1000000 9
b1000000 <
b10000 /
0*
b10 (
b10 0
b1000000 ,
1!
#375000
0!
#380000
b101 &
b101 3
b11 (
b11 0
1!
#385000
0!
#390000
b110 &
b110 3
0?
0>
b101 (
b101 0
1!
#395000
0!
#400000
b10001 5
b111 &
b111 3
16
b110 (
b110 0
1!
#405000
0!
#410000
b1000000 :
b1001 &
b1001 3
b10 ;
06
01
b1111111111010001 2
b111 (
b111 0
b10001 4
1!
#415000
0!
#420000
b1100000 9
b1111111110010001 2
b10000 -
b100000 8
b10000000 <
b11 &
b11 3
b0 ;
1.
b1000000 %
b1000000 7
b1001 (
b1001 0
1!
#425000
0!
#430000
b1111111111000001 2
b101 &
b101 3
0.
b110000 9
b1010000 <
b100 /
b11 (
b11 0
b10000 ,
1!
#435000
0!
#440000
b1000 &
b1000 3
b101 (
b101 0
1!
#445000
0!
#450000
b100000 :
b1001 &
b1001 3
b1 ;
b1000 (
b1000 0
1!
#455000
0!
#460000
b100000 9
b1111111111100001 2
b100 -
b10000 8
b110000 <
b11 &
b11 3
b0 ;
1.
b100000 %
b100000 7
b1001 (
b1001 0
1!
#465000
0!
#470000
b1111111111101101 2
b101 &
b101 3
0.
b10100 9
b100100 <
b1 /
b11 (
b11 0
b100 ,
1!
#475000
0!
#480000
b1000 &
b1000 3
b101 (
b101 0
1!
#485000
0!
#490000
b10000 :
b1001 &
b1001 3
b1 ;
b1000 (
b1000 0
1!
#495000
0!
#500000
b1100 9
b1111111111111101 2
b1 -
b1000 8
b10100 <
b11 &
b11 3
b0 ;
1.
b10000 %
b10000 7
b1001 (
b1001 0
1!
#505000
0!
#510000
11
b0 2
b101 &
b101 3
0.
b1001 9
b10001 <
b0 /
b11 (
b11 0
b1 ,
1!
#515000
0!
#520000
b110 &
b110 3
b101 (
b101 0
1!
#525000
0!
#530000
b0 5
b111 &
b111 3
16
b110 (
b110 0
1!
#535000
0!
#540000
b1001 :
b1111111111101111 2
01
b1001 &
b1001 3
b10 ;
06
b0 4
b111 (
b111 0
1!
#545000
0!
#550000
b0 -
b101 9
b1111111111110110 2
b11 &
b11 3
b0 ;
1.
b100 8
b1010 <
b1001 (
b1001 0
b1001 %
b1001 7
1!
#555000
0!
#560000
b1111111111110111 2
b100 9
b1001 <
0+
b1010 &
b1010 3
0.
b0 ,
b11 (
b11 0
1!
#565000
0!
#570000
b0 &
b0 3
1=
1'
b1010 (
b1010 0
1!
#575000
0!
#580000
b1011111111110111 2
b100000000000100 9
b100000000001001 <
1+
b1000000000000 /
1*
b100000000000000 -
1?
1>
0'
b100000000000000 ,
b0 (
b0 0
1!
