Task3/Layered/Top/amba_apb_slave.sv
module amba_apb_slave
(input pclk,preset,psel,penable,pwrite,
input [7:0]paddr,pwdata,
output reg pready,
output reg [7:0]prdata);

reg [7:0] mem [63:0];
integer i;

always @(posedge pclk)
begin
	if(preset) begin
		prdata <= 8'b0;
		for(i=0;i<=63;i=i+1)
			mem[i] <= 0;
	end
	else
	begin
		if((psel==1'b1)&&(penable==1'b1)&&(pwrite==1'b1))
			mem[paddr]<=pwdata;
		else
		if((psel==1'b1)&&(penable==1'b1)&&(pwrite==1'b0)) begin
			prdata<=mem[paddr];
		end
	end
end
always @(posedge pclk)
begin
if(psel==1'b1&&penable==1'b1)
	pready = 1'b1;
else
	pready = 1'b0;
end
initial begin
	 $dumpfile("dump.vcd");
	 $dumpvars;
end
endmodule

Task3/Layered/APB Master/amba_apb_master.sv
module amba_apb_master (input pclk,preset,transfer,mpwrite,pready,
input [7:0] apb_write_paddr,apb_write_data,apb_read_paddr,prdata,
output reg psel,penable,spwrite,
output reg [7:0]paddr,pwdata,apb_read_data_out);


reg [1:0] state,next;

parameter IDLE = 2'b00,
	  SETUP = 2'b01,
	  ACCESS = 2'b10;

always @(posedge pclk)
begin
	if(preset)
		state= IDLE;
	else
		state = next;
end

always @(state,transfer,mpwrite,pready,apb_write_paddr,apb_write_data,apb_read_paddr,prdata)
begin
paddr = apb_write_paddr;
pwdata = apb_write_data;
spwrite = mpwrite;
	case(state)
		IDLE:begin
		     if(transfer)
			next=SETUP;
		     else
		     begin
			next = IDLE;
			apb_read_data_out = 8'b0;
			psel = 0;
			penable = 0;
			paddr = 0;
			pwdata = 0;
		     end
		     end
		
		SETUP:begin
		      next = ACCESS;
		      psel = 1'b1;
		      penable = 1'b0;
		      end
		
		ACCESS: begin
			psel = 1'b1;
			penable = 1'b1;
			if(pready==1'b1 && transfer == 1'b1)
			next = SETUP;
			else if (pready == 1'b1 && transfer == 1'b0)
			next = IDLE;
			else if(pready == 1'b0)
			next = ACCESS;
			end
		endcase
	
end

initial begin
	$dumpfile("dump.vcd");
	$dumpvars;
end
endmodule

Task3/Layered/Top/top_amba_apb.sv
//top_amba_apb
`include "amba_apb_master.sv"
`include "amba_apb_slave.sv"
module top_amba_apb(input pclk,preset,transfer,mpwrite,
input [7:0] apb_write_paddr,apb_write_data,apb_read_paddr,
output reg [7:0]prdata,apb_read_data_out ,output psel,penable);

wire pready,pwrite;
wire [7:0] paddr,pwdata;

amba_apb_master a1(.pclk(pclk),.preset(preset),.transfer(transfer),.mpwrite(mpwrite),.pready(pready),
.apb_write_paddr(apb_write_paddr),.apb_write_data(apb_write_data),.apb_read_paddr(apb_read_paddr),.prdata(prdata),
.psel(psel),.penable(penable),.spwrite(pwrite),.paddr(paddr),.pwdata(pwdata),.apb_read_data_out(apb_read_data_out));

amba_apb_slave a2(.pclk(pclk),.preset(preset),.psel(psel),.penable(penable),.pwrite(pwrite),
.paddr(paddr),.pwdata(pwdata),.pready(pready),.prdata(prdata));


initial begin
    $dumpfile("dump.vcd");
    $dumpvars(0,top_amba_apb);
end

endmodule

Task3/Layered/Top/dump.vcd
$date
	Wed Oct 13 21:17:51 2021
$end
$version
	Icarus Verilog
$end
$timescale
	1ps
$end
$scope module top_amba_apb $end
$var wire 8 ! apb_read_paddr [7:0] $end
$var wire 8 " apb_write_data [7:0] $end
$var wire 8 # apb_write_paddr [7:0] $end
$var wire 1 $ mpwrite $end
$var wire 1 % pclk $end
$var wire 1 & preset $end
$var wire 1 ' transfer $end
$var wire 1 ( pwrite $end
$var wire 8 ) pwdata [7:0] $end
$var wire 1 * psel $end
$var wire 1 + pready $end
$var wire 8 , prdata [7:0] $end
$var wire 1 - penable $end
$var wire 8 . paddr [7:0] $end
$var wire 8 / apb_read_data_out [7:0] $end
$scope module a1 $end
$var wire 8 0 apb_read_paddr [7:0] $end
$var wire 8 1 apb_write_data [7:0] $end
$var wire 8 2 apb_write_paddr [7:0] $end
$var wire 1 $ mpwrite $end
$var wire 1 % pclk $end
$var wire 1 & preset $end
$var wire 1 ' transfer $end
$var wire 1 + pready $end
$var wire 8 3 prdata [7:0] $end
$var reg 8 4 apb_read_data_out [7:0] $end
$var reg 2 5 next [1:0] $end
$var reg 8 6 paddr [7:0] $end
$var reg 1 - penable $end
$var reg 1 * psel $end
$var reg 8 7 pwdata [7:0] $end
$var reg 1 ( spwrite $end
$var reg 2 8 state [1:0] $end
$upscope $end
$scope module a2 $end
$var wire 8 9 paddr [7:0] $end
$var wire 1 % pclk $end
$var wire 1 - penable $end
$var wire 1 & preset $end
$var wire 1 * psel $end
$var wire 8 : pwdata [7:0] $end
$var wire 1 ( pwrite $end
$var reg 8 ; prdata [7:0] $end
$var reg 1 + pready $end
$var integer 32 < i [31:0] $end
$upscope $end
$upscope $end
$scope module top_amba_apb $end
$scope module a1 $end
$upscope $end
$scope module a2 $end
$upscope $end
$upscope $end
$enddefinitions $end
#0
$dumpvars
bx <
bx ;
b0 :
b0 9
bx 8
b0 7
b0 6
bx 5
bx 4
bx 3
b0 2
b0 1
b0 0
bx /
b0 .
x-
bx ,
0+
x*
b0 )
0(
0'
1&
1%
0$
b0 #
b0 "
b0 !
$end
#5000
0%
#10000
1(
b10100 )
b10100 7
b10100 :
b1010 .
b1010 6
b1010 9
0&
1'
1$
b1010 #
b1010 2
b10100 "
b10100 1
b0 ,
b0 3
b0 ;
0-
0*
b0 /
b0 4
b1 5
b1000000 <
b0 8
1%
#15000
0%
#20000
1*
b10 5
b1 8
1%
#25000
0%
#30000
1-
b10 8
1%
#35000
0%
#40000
b1 5
1+
1%
#45000
0%
#50000
0-
b10 5
b1 8
1%
#55000
0%
#60000
0(
0$
1-
b10 8
0+
1%
#65000
0%
#70000
b10100 ,
b10100 3
b10100 ;
b1 5
1+
1%
#75000
0%
#80000
0-
b10 5
b1 8
1%
#85000
0%
#90000
1-
0+
b10 8
1%
