Task3/Layered/APB Slave/amba_apb_slave.sv

module amba_apb_slave
(input pclk,preset,psel,penable,pwrite,
input [7:0]paddr,pwdata,
output reg pready,
output reg [7:0]prdata,

output reg [7:0] mem [63:0]);

integer i;
always @(posedge pclk)
begin
	pready = 0;
	if(preset) begin
		prdata <= 8'b0;
		for(i=0;i<=63;i++)
		  	mem[i] <= 8'b0;
	end else
	begin
		if((psel==1'b1)&&(penable==1'b1)&&(pwrite==1'b1)) begin
			mem[paddr] <= pwdata;
			pready <= 1;
		end else 
		if((psel==1'b1)&&(penable==1'b1)&&(pwrite==1'b0)) begin
			prdata <= mem[paddr];
			pready <= 1;
		end
	end
end

	initial begin
		pready = 0;
		$dumpfile("dump.vcd");
		$dumpvars;
	end
endmodule

Task3/Layered/APB Slave/dump.vcd
$date
	Mon Oct 11 18:40:02 2021
$end
$version
	Icarus Verilog
$end
$timescale
	1ps
$end
$scope module amba_apb_slave $end
$var wire 8 ! paddr [7:0] $end
$var wire 1 " pclk $end
$var wire 1 # penable $end
$var wire 1 $ preset $end
$var wire 1 % psel $end
$var wire 8 & pwdata [7:0] $end
$var wire 1 ' pwrite $end
$var reg 8 ( prdata [7:0] $end
$var reg 1 ) pready $end
$var integer 32 * i [31:0] $end
$upscope $end
$enddefinitions $end
#0
$dumpvars
b1000000 *
0)
b0 (
0'
b0 &
0%
1$
0#
1"
b0 !
$end
#5000
0"
#10000
0$
1%
b1000000 *
1"
#15000
0"
#20000
1)
1#
1'
b101 !
b1010 &
1"
#25000
0"
#30000
1"
#35000
0"
#40000
0)
0#
1"
#45000
0"
#50000
1"
#55000
0"
#60000
1)
1#
0'
1"
#65000
0"
#70000
b1010 (
1"
#75000
0"
#80000
0)
0#
1"
#85000
0"
#90000
1"
#95000
0"
#100000
1)
1#
b1 !
1"
#105000
0"
#110000
b0 (
1"
#115000
0"
#120000
0)
0#
1"
